lishiyu/__init__.py
lishiyu/lishiyu.py
src/__init__.py
src/lishiyu.py
lishiyu-0.0.2.dist-info/LICENSE
lishiyu-0.0.2.dist-info/METADATA
lishiyu-0.0.2.dist-info/WHEEL
lishiyu-0.0.2.dist-info/top_level.txt
lishiyu-0.0.2.dist-info/RECORD
