Metadata-Version: 2.1
Name: lishiyu
Version: 0.0.2
Summary: PP - Personal Package
Home-page: https://github.com/shiyuli/lishiyu
Author: lishiyu
Author-email: author@example.com
License: UNKNOWN
Platform: UNKNOWN
Classifier: Programming Language :: Python :: 3
Classifier: License :: OSI Approved :: MIT License
Classifier: Operating System :: OS Independent
